{
  "project_info": {
    "project_number": "787491011636",
    "project_id": "fir-test-5e156",
    "storage_bucket": "fir-test-5e156.appspot.com"
  },
  "client": [
    {
      "client_info": {
        "mobilesdk_app_id": "1:787491011636:android:f744b422bc2a22b5e49e61",
        "android_client_info": {
          "package_name": "com.example.firebase_test"
        }
      },
      "oauth_client": [
        {
          "client_id": "787491011636-7de945p5o0mguhb3e6un6c5776biu5m5.apps.googleusercontent.com",
          "client_type": 3
        }
      ],
      "api_key": [
        {
          "current_key": "AIzaSyDwfoZe-qgYJp2CN-8P3omra6SST_UsePA"
        }
      ],
      "services": {
        "appinvite_service": {
          "other_platform_oauth_client": [
            {
              "client_id": "787491011636-7de945p5o0mguhb3e6un6c5776biu5m5.apps.googleusercontent.com",
              "client_type": 3
            },
            {
              "client_id": "787491011636-g4lplm9ofr3d93oov8tc1vvg1lbtqbqc.apps.googleusercontent.com",
              "client_type": 2,
              "ios_info": {
                "bundle_id": "com.example.firebaseTest"
              }
            }
          ]
        }
      }
    }
  ],
  "configuration_version": "1"
}